poptimizer/__init__.py
poptimizer/poptimizer.py
poptimizer/prompts.py
poptimizer-0.0.4.dist-info/LICENSE
poptimizer-0.0.4.dist-info/METADATA
poptimizer-0.0.4.dist-info/WHEEL
poptimizer-0.0.4.dist-info/top_level.txt
poptimizer-0.0.4.dist-info/RECORD
