Metadata-Version: 2.1
Name: poptimizer
Version: 0.0.4
Summary: Utilize Large Language Models to Automatically Optimize Prompts for LLM Application Development
Author: alkhalifas
License-File: LICENSE
Requires-Dist: fastapi
Requires-Dist: langchain
Requires-Dist: openai
Requires-Dist: pylint
